ws_joint_sbom_reports/__init__.py
ws_joint_sbom_reports/_version.py
ws_joint_sbom_reports/joint_sbom_reports.py
ws_joint_sbom_reports/tests/__init__.py
ws_joint_sbom_reports/tests/test_ws_joint_sbom_reports.py
ws_joint_sbom_reports-0.0.4.dist-info/LICENSE
ws_joint_sbom_reports-0.0.4.dist-info/METADATA
ws_joint_sbom_reports-0.0.4.dist-info/WHEEL
ws_joint_sbom_reports-0.0.4.dist-info/entry_points.txt
ws_joint_sbom_reports-0.0.4.dist-info/top_level.txt
ws_joint_sbom_reports-0.0.4.dist-info/RECORD
