Metadata-Version: 2.1
Name: ws-joint-sbom-reports
Version: 0.0.4
Summary: Joint two SBOM files in JSON format
Home-page: https://github.com/whitesource-ps/ws-joint-sbom-reports
Author: WhiteSource Professional Services
Author-email: ps@whitesourcesoftware.com
License: LICENSE
Platform: UNKNOWN
Classifier: Programming Language :: Python :: 3.9
Classifier: Programming Language :: Python :: 3.10
Classifier: License :: OSI Approved :: Apache Software License
Classifier: Operating System :: OS Independent
Requires-Python: >=3.9
License-File: LICENSE
